ripe.atlas.tools-3.2.0-py3.13-nspkg.pth
ripe/atlas/tools/__init__.py
ripe/atlas/tools/cache.py
ripe/atlas/tools/exceptions.py
ripe/atlas/tools/filters.py
ripe/atlas/tools/ipdetails.py
ripe/atlas/tools/streaming.py
ripe/atlas/tools/version.py
ripe/atlas/tools/aggregators/__init__.py
ripe/atlas/tools/aggregators/base.py
ripe/atlas/tools/commands/__init__.py
ripe/atlas/tools/commands/alias.py
ripe/atlas/tools/commands/base.py
ripe/atlas/tools/commands/configure.py
ripe/atlas/tools/commands/go.py
ripe/atlas/tools/commands/measurement_info.py
ripe/atlas/tools/commands/measurement_search.py
ripe/atlas/tools/commands/probe_info.py
ripe/atlas/tools/commands/probe_search.py
ripe/atlas/tools/commands/report.py
ripe/atlas/tools/commands/shibboleet.py
ripe/atlas/tools/commands/stream.py
ripe/atlas/tools/commands/measure/__init__.py
ripe/atlas/tools/commands/measure/base.py
ripe/atlas/tools/commands/measure/dns.py
ripe/atlas/tools/commands/measure/http.py
ripe/atlas/tools/commands/measure/ntp.py
ripe/atlas/tools/commands/measure/ping.py
ripe/atlas/tools/commands/measure/spec.py
ripe/atlas/tools/commands/measure/sslcert.py
ripe/atlas/tools/commands/measure/traceroute.py
ripe/atlas/tools/helpers/__init__.py
ripe/atlas/tools/helpers/actions.py
ripe/atlas/tools/helpers/colours.py
ripe/atlas/tools/helpers/rendering.py
ripe/atlas/tools/helpers/sanitisers.py
ripe/atlas/tools/helpers/tabular.py
ripe/atlas/tools/helpers/validators.py
ripe/atlas/tools/helpers/xdg.py
ripe/atlas/tools/probes/__init__.py
ripe/atlas/tools/renderers/__init__.py
ripe/atlas/tools/renderers/aggregate_ping.py
ripe/atlas/tools/renderers/base.py
ripe/atlas/tools/renderers/dns.py
ripe/atlas/tools/renderers/dns_compact.py
ripe/atlas/tools/renderers/dst_asn.py
ripe/atlas/tools/renderers/http.py
ripe/atlas/tools/renderers/ntp.py
ripe/atlas/tools/renderers/ping.py
ripe/atlas/tools/renderers/raw.py
ripe/atlas/tools/renderers/ssl_consistency.py
ripe/atlas/tools/renderers/sslcert.py
ripe/atlas/tools/renderers/traceroute.py
ripe_atlas_tools-3.2.0.dist-info/licenses/LICENSE
ripe_atlas_tools-3.2.0.dist-info/METADATA
ripe_atlas_tools-3.2.0.dist-info/WHEEL
ripe_atlas_tools-3.2.0.dist-info/namespace_packages.txt
ripe_atlas_tools-3.2.0.dist-info/top_level.txt
ripe_atlas_tools-3.2.0.dist-info/RECORD
