Metadata-Version: 2.4
Name: ripe.atlas.tools
Version: 3.2.0
Summary: The official command line client for RIPE Atlas
Home-page: https://github.com/RIPE-NCC/ripe-atlas-tools
Download-URL: https://github.com/RIPE-NCC/ripe-atlas-tools
Author: The RIPE Atlas team
Author-email: atlas@ripe.net
Maintainer: The RIPE Atlas team
Maintainer-email: atlas@ripe.net
License: GPLv3
Keywords: RIPE,RIPE NCC,RIPE Atlas,Command Line
Classifier: License :: OSI Approved :: GNU General Public License v3 (GPLv3)
Classifier: Operating System :: POSIX
Classifier: Operating System :: Unix
Classifier: Programming Language :: Python :: 3.9
Classifier: Programming Language :: Python :: 3.10
Classifier: Programming Language :: Python :: 3.11
Classifier: Programming Language :: Python :: 3.12
Classifier: Programming Language :: Python :: 3.13
Classifier: Topic :: Internet :: WWW/HTTP
License-File: LICENSE
Requires-Dist: IPy
Requires-Dist: python-dateutil
Requires-Dist: requests>=2.7.0
Requires-Dist: urllib3<2
Requires-Dist: ripe.atlas.cousteau<3,>=2
Requires-Dist: ripe.atlas.sagan<2,>=1.2
Requires-Dist: tzlocal
Requires-Dist: pyyaml
Requires-Dist: pyOpenSSL>=0.13
Requires-Dist: typing-extensions
Provides-Extra: doc
Requires-Dist: sphinx; extra == "doc"
Requires-Dist: sphinx_rtd_theme; extra == "doc"
Provides-Extra: fast
Requires-Dist: ujson; extra == "fast"
Dynamic: author
Dynamic: author-email
Dynamic: classifier
Dynamic: description
Dynamic: download-url
Dynamic: home-page
Dynamic: keywords
Dynamic: license
Dynamic: license-file
Dynamic: maintainer
Dynamic: maintainer-email
Dynamic: provides-extra
Dynamic: requires-dist
Dynamic: summary
